{
  "name": "integration-tester",
  "repo": "segmentio/analytics.js-integration-tester",
  "description": "Helper to quickly test an analytics.js integration.",
  "version": "1.4.2",
  "license": "MIT",
  "keywords": [
    "integration",
    "tester"
  ],
  "dependencies": {
    "component/assert": "*",
    "component/domify": "*",
    "component/each": "*",
    "component/indexof": "*",
    "ianstormtaylor/is": "*",
    "jkroso/equals": "*",
    "matthewp/keys": "*",
    "segmentio/spy": "*",
    "segmentio/stub": "*",
    "yields/fmt": "*"
  },
  "development": {
    "segmentio/analytics.js-core": "*",
    "segmentio/analytics.js-integration": "^1.0.0",
    "segmentio/facade": "*"
  },
  "main": "index.js",
  "scripts": [
    "index.js"
  ]
}
